ovos_jabir_solver/__init__.py
ovos_jabir_solver/version.py
ovos_solver_jabir_plugin-0.0.0a4.dist-info/METADATA
ovos_solver_jabir_plugin-0.0.0a4.dist-info/WHEEL
ovos_solver_jabir_plugin-0.0.0a4.dist-info/entry_points.txt
ovos_solver_jabir_plugin-0.0.0a4.dist-info/top_level.txt
ovos_solver_jabir_plugin-0.0.0a4.dist-info/zip-safe
ovos_solver_jabir_plugin-0.0.0a4.dist-info/RECORD
