Metadata-Version: 2.1
Name: ovos-solver-jabir-plugin
Version: 0.0.0a4
Summary: A question solver plugin for OVOS
Home-page: https://github.com/TigreGotico/ovos-solver-jabir-plugin
Author: jarbasai
Author-email: jarbasai@mailfence.com
License: MIT
Keywords: OVOS openvoiceos LLM plugin utterance fallback query
Platform: UNKNOWN
Requires-Dist: ovos-plugin-manager
Requires-Dist: huggingface-hub
Requires-Dist: llama-cpp-python
